al_otto-0.2.2.dist-info/METADATA
al_otto-0.2.2.dist-info/WHEEL
otto/__init__.py
otto/_version.py
otto/chartransitions.py
otto/cliparse.py
otto/colortransitions.py
otto/config.py
otto/config_otto.json
otto/examples/config_otto.json
otto/examples/data.csv
otto/examples/data.json
otto/examples/example.json
otto/examples/export.json
otto/examples/otto.json
otto/examples/talavideo.json
otto/exceptions.py
otto/export.sh
otto/getdata.py
otto/log.py
otto/main.py
otto/models.py
otto/preview.py
otto/render.py
otto/templates.py
otto/templates/VideoForm.html
otto/utils.py
al_otto-0.2.2.dist-info/RECORD
