Metadata-Version: 2.1
Name: al-otto
Version: 0.2.2
Summary: The ottomatic video engine
Home-page: https://github.com/quaternionmedia/otto
Author-Email: Quaternion Media <qm@quaternion.media>
License: MIT
Project-URL: Homepage, https://github.com/quaternionmedia/otto
Project-URL: Documentation, https://quaternionmedia.github.io/otto/
Project-URL: Repository, https://github.com/quaternionmedia/otto
Requires-Python: <4.0,>=3.8.1
Requires-Dist: fastapi~=0.95
Requires-Dist: moviepy~=1.0
Requires-Dist: pydantic~=1.10
Requires-Dist: gizeh~=0.1; extra == "render"
Requires-Dist: bezier~=2021.2; extra == "render"
Requires-Dist: tqdm~=4.65; extra == "render"
Requires-Dist: pytest~=7.3; extra == "test"
Requires-Dist: httpx~=0.24; extra == "test"
Requires-Dist: pytest-cov~=4.0; extra == "test"
Requires-Dist: pytest-xdist~=3.2; extra == "test"
Requires-Dist: mkdocs~=1.4; extra == "docs"
Requires-Dist: mkdocs-material~=9.1; extra == "docs"
Requires-Dist: mkdocs-git-revision-date-localized-plugin~=1.2; extra == "docs"
Requires-Dist: mike~=1.1; extra == "docs"
Requires-Dist: mkdocstrings[python]~=0.21; extra == "docs"
Requires-Dist: setuptools~=67.6; extra == "docs"
Provides-Extra: render
Provides-Extra: test
Provides-Extra: docs
